Metadata-Version: 2.1
Name: django-postgres-dropdb
Version: 2020.7.1
Summary: drop postgres database
Home-page: https://github.com/andrewp-as-is/django-postgres-dropdb.py
License: Unlicense
Keywords: django postgres dropdb
Platform: UNKNOWN
Classifier: Framework :: Django
Classifier: License :: Public Domain
Classifier: Operating System :: OS Independent
Classifier: Programming Language :: Python :: 3
